Metadata-Version: 1.0
Name: UsingPy
Version: 0.2
Summary: C# Using in Python
Home-page: http://github.com/BatDev0/UsingPy
Author: BatDev0
Author-email: Brody@tntsplash.net
License: MIT
Platform: UNKNOWN
